{
  "version": "7",
  "dialect": "postgresql",
  "entries": [
    {
      "idx": 0,
      "version": "7",
      "when": 1768525884469,
      "tag": "0000_romantic_lester",
      "breakpoints": true
    },
    {
      "idx": 1,
      "version": "7",
      "when": 1768792442774,
      "tag": "0001_demonic_namora",
      "breakpoints": true
    },
    {
      "idx": 2,
      "version": "7",
      "when": 1768793199127,
      "tag": "0002_steep_epoch",
      "breakpoints": true
    },
    {
      "idx": 3,
      "version": "7",
      "when": 1768841272053,
      "tag": "0003_dry_marvel_apes",
      "breakpoints": true
    },
    {
      "idx": 4,
      "version": "7",
      "when": 1769047472378,
      "tag": "0004_condemned_scorpion",
      "breakpoints": true
    }
  ]
}